CHANGELOG.md
LICENSE
MANIFEST.in
README.md
pytest.ini
setup.py
tox.ini
extenum/__init__.py
extenum/constant_specific.py
extenum/enumset.py
extenum/implicit_enum.py
extenum.egg-info/PKG-INFO
extenum.egg-info/SOURCES.txt
extenum.egg-info/dependency_links.txt
extenum.egg-info/top_level.txt
tests/test_common_behavior.py
tests/test_constant_specific.py
tests/test_enumset.py
tests/test_implicit_enum.py