Metadata-Version: 2.1
Name: extenum
Version: 0.8.1
Summary: Extended Enum classes for the Python 3 enum module
Home-page: https://github.com/t2y/extenum
Author: Tetsuya Morimoto
Author-email: tetsuya.morimoto@gmail.com 
License: Apache License 2.0
Keywords: enum
Platform: unix
Platform: linux
Platform: osx
Platform: windows
Classifier: License :: OSI Approved :: Apache Software License
Classifier: Development Status :: 4 - Beta
Classifier: Intended Audience :: Developers
Classifier: Operating System :: Microsoft :: Windows
Classifier: Operating System :: MacOS :: MacOS X
Classifier: Operating System :: POSIX
Classifier: Programming Language :: Python :: 3
Classifier: Programming Language :: Python :: 3.6
Classifier: Programming Language :: Python :: 3.7
Classifier: Programming Language :: Python :: 3.8
Classifier: Programming Language :: Python :: 3.9
Classifier: Programming Language :: Python :: 3 :: Only
Classifier: Programming Language :: Python :: Implementation :: CPython
Classifier: Programming Language :: Python :: Implementation :: PyPy
Classifier: Topic :: Software Development :: Libraries
